odoo/addons/l10n_fr_intrastat_service/README.rst
odoo/addons/l10n_fr_intrastat_service/__init__.py
odoo/addons/l10n_fr_intrastat_service/__manifest__.py
odoo/addons/l10n_fr_intrastat_service/data/des.xsd
odoo/addons/l10n_fr_intrastat_service/data/intrastat_service_reminder.xml
odoo/addons/l10n_fr_intrastat_service/i18n/am.po
odoo/addons/l10n_fr_intrastat_service/i18n/ca.po
odoo/addons/l10n_fr_intrastat_service/i18n/de.po
odoo/addons/l10n_fr_intrastat_service/i18n/el_GR.po
odoo/addons/l10n_fr_intrastat_service/i18n/es.po
odoo/addons/l10n_fr_intrastat_service/i18n/es_ES.po
odoo/addons/l10n_fr_intrastat_service/i18n/fi.po
odoo/addons/l10n_fr_intrastat_service/i18n/fr.po
odoo/addons/l10n_fr_intrastat_service/i18n/gl.po
odoo/addons/l10n_fr_intrastat_service/i18n/it.po
odoo/addons/l10n_fr_intrastat_service/i18n/l10n_fr_intrastat_service.pot
odoo/addons/l10n_fr_intrastat_service/i18n/nb_NO.po
odoo/addons/l10n_fr_intrastat_service/i18n/pt.po
odoo/addons/l10n_fr_intrastat_service/i18n/pt_BR.po
odoo/addons/l10n_fr_intrastat_service/i18n/pt_PT.po
odoo/addons/l10n_fr_intrastat_service/i18n/sl.po
odoo/addons/l10n_fr_intrastat_service/i18n/tr.po
odoo/addons/l10n_fr_intrastat_service/models/__init__.py
odoo/addons/l10n_fr_intrastat_service/models/intrastat_service.py
odoo/addons/l10n_fr_intrastat_service/readme/CONTRIBUTORS.rst
odoo/addons/l10n_fr_intrastat_service/readme/DESCRIPTION.rst
odoo/addons/l10n_fr_intrastat_service/readme/USAGE.rst
odoo/addons/l10n_fr_intrastat_service/report/__init__.py
odoo/addons/l10n_fr_intrastat_service/report/intrastat_service_report_xls.py
odoo/addons/l10n_fr_intrastat_service/security/intrastat_service_security.xml
odoo/addons/l10n_fr_intrastat_service/security/ir.model.access.csv
odoo/addons/l10n_fr_intrastat_service/static/description/icon.png
odoo/addons/l10n_fr_intrastat_service/static/description/index.html
odoo/addons/l10n_fr_intrastat_service/tests/__init__.py
odoo/addons/l10n_fr_intrastat_service/tests/test_fr_intrastat_service.py
odoo14_addon_l10n_fr_intrastat_service-14.0.1.2.0.dist-info/METADATA
odoo14_addon_l10n_fr_intrastat_service-14.0.1.2.0.dist-info/WHEEL
odoo14_addon_l10n_fr_intrastat_service-14.0.1.2.0.dist-info/top_level.txt
odoo14_addon_l10n_fr_intrastat_service-14.0.1.2.0.dist-info/RECORD
