Metadata-Version: 2.1
Name: odoo14-addon-l10n_fr_intrastat_service
Version: 14.0.1.2.0
Summary: Module for Intrastat service reporting (DES) for France
Home-page: https://github.com/OCA/l10n-france
Author: Akretion,Odoo Community Association (OCA)
Author-email: support@odoo-community.org
License: AGPL-3
Classifier: Programming Language :: Python
Classifier: Framework :: Odoo
Classifier: Framework :: Odoo :: 14.0
Classifier: License :: OSI Approved :: GNU Affero General Public License v3
Requires-Python: >=3.6
Requires-Dist: odoo14-addon-intrastat-base
Requires-Dist: odoo14-addon-report-xlsx-helper
Requires-Dist: odoo<14.1dev,>=14.0a
Requires-Dist: python-stdnum
